{"name":"Aldino","health":50,"maxHealth":100,"inventory":[{"name":"Kayu Ajaib","description":"kayu yang dapat berubah bentuk sesuai dengan keinginan pemakainya","canBeTaken":true},{"name":"Kulit Hewan Besar","description":"dapat digunakan sebagai baju pelindung","canBeTaken":true},{"name":"Sekop Berkarat","description":"sekop yang digunakan untuk mengubur harta karun yang tertinggal","canBeTaken":true},{"name":"Batang Pohon Besar","description":"dapat digunakan sebagai sekoci untuk melewati sungai","canBeTaken":true},{"name":"Cawan Kuno","description":"cawan yang berasal dari suku kuno","canBeTaken":true},{"name":"Pisau Batu","description":"pisau yang terbuat dari batu yang diukir","canBeTaken":true},{"name":"Kitab Petunjuk","description":"kitab yang menunjukkan peta menuju suatu tempat tersembunyi","canBeTaken":true}],"currentRoomName":"Templar Kuno"}